arches_templating/__init__.py
arches_templating/admin.py
arches_templating/apps.py
arches_templating/models.py
arches_templating/tests.py
arches_templating/urls.py
arches_templating/management/__init__.py
arches_templating/management/commands/__init__.py
arches_templating/management/commands/load_template.py
arches_templating/migrations/0001_initial.py
arches_templating/migrations/__init__.py
arches_templating/template_engine/__init__.py
arches_templating/template_engine/template_engine.py
arches_templating/template_engine/template_engine_factory.py
arches_templating/template_engine/template_tag.py
arches_templating/template_engine/template_tag_type.py
arches_templating/template_engine/implementations/__init__.py
arches_templating/template_engine/implementations/docx_template_engine.py
arches_templating/template_engine/implementations/pptx_template_engine.py
arches_templating/template_engine/implementations/xlsx_template_engine.py
arches_templating/templates/index.html
arches_templating/views/__init__.py
arches_templating/views/index.py
arches_templating/views/template.py
arches_templating-0.1.2.dist-info/METADATA
arches_templating-0.1.2.dist-info/WHEEL
arches_templating-0.1.2.dist-info/top_level.txt
arches_templating-0.1.2.dist-info/RECORD
