Metadata-Version: 2.1
Name: arches-templating
Version: 0.1.2
Summary: Arches templating provides an extensible templating engine for various file types
Home-page: http://archesproject.org/
Author: Farallon Geographics, Inc
Author-email: dev@fargeo.com
License: GNU AGPL3
Keywords: django arches cultural heritage
Platform: UNKNOWN
Classifier: Development Status :: 5 - Production/Stable
Classifier: Intended Audience :: Developers
Classifier: Intended Audience :: Science/Research
Classifier: Intended Audience :: Information Technology
Classifier: Topic :: Software Development :: Build Tools
Classifier: Programming Language :: Python :: 3
Classifier: Programming Language :: Python :: 3.7
Classifier: Framework :: Django :: 1.11
Classifier: License :: OSI Approved :: GNU General Public License v3 (GPLv3)
Requires-Dist: Django >=3.2.18
Requires-Dist: python-pptx >=0.6.21
Requires-Dist: python-docx !=1.0.0,>=0.8.11
Requires-Dist: openpyxl >=3.0.7
Requires-Dist: PyYAML >=6.0
